boxdenat/__init__.py
boxdenat/actions.py
boxdenat/orders.py
boxdenat/plugin.py
boxdenat/points.py
boxdenat/ui.py
boxdenat/menu/__init__.py
boxdenat/menu/model.py
boxdenat/menu/parser.py
boxdenat/menu/provider.py
antibot_boxdenat-2.0.6.dist-info/LICENSE
antibot_boxdenat-2.0.6.dist-info/METADATA
antibot_boxdenat-2.0.6.dist-info/WHEEL
antibot_boxdenat-2.0.6.dist-info/entry_points.txt
antibot_boxdenat-2.0.6.dist-info/top_level.txt
antibot_boxdenat-2.0.6.dist-info/RECORD
